gemlog/gemconvert.py
gemlog/version.py
gemlog/xcorr.py
gemlog/gem_network.py
gemlog/__init__.py
gemlog/core.py
gemlog/gemconvert_single.py
gemlog/gemlog_aux.py
gemlog/parsers.cpython-312-darwin.so
gemlog/gem_cat.py
gemlog/huddle_test.py
gemlog/parsers.pyx
gemlog/data/response/datalogger/RESP.XX.GM000..HHZ.GEMINFRAV0.0.100
gemlog/data/response/datalogger/RESP.XX.GM002..HHZ.GEMINFRAV1.0.100
gemlog/data/response/datalogger/RESP.XX.GM001..HHZ.GEMINFRAV1.1.100
gemlog/data/response/sensor/RESP.XX.IS000..BDF.GEMV0.26.0_0016
gemlog/data/response/sensor/RESP.XX.IS000..BDF.GEMV0.26.0_0005
gemlog/data/response/sensor/RESP.XX.IS000..BDF.GEMV0.26.0_0023
gemlog/data/response/sensor/RESP.XX.IS025..BDF.GEMV1.26.0_0022
gemlog/data/noise/IMSNOISE_MIN_MED_MAX.txt
gemlog/data/noise/Gem_v0.98_Noise_spec.txt
gemlog-1.7.10.dist-info/RECORD
gemlog-1.7.10.dist-info/LICENSE
gemlog-1.7.10.dist-info/WHEEL
gemlog-1.7.10.dist-info/entry_points.txt
gemlog-1.7.10.dist-info/top_level.txt
gemlog-1.7.10.dist-info/METADATA
